Metadata-Version: 2.1
Name: lstosa
Version: 0.11.6
Summary: Onsite analysis pipeline for the CTA LST-1
Author: María Láinez, José Enrique Ruiz, Lab Saha, Andrés Baquero, José Luis Contreras, Maximilian Linhoff
Author-email: Daniel Morcuende <dmorcuen@ucm.es>
License: BSD-3-Clause
Project-URL: repository, https://github.com/cta-observatory/lstosa
Project-URL: documentation, https://lstosa.readthedocs.io/
Classifier: Development Status :: 4 - Beta
Classifier: License :: OSI Approved :: BSD License
Classifier: Intended Audience :: Science/Research
Classifier: Topic :: Scientific/Engineering :: Astronomy
Classifier: Topic :: Scientific/Engineering :: Physics
Classifier: Programming Language :: Python :: 3
Classifier: Programming Language :: Python :: 3.10
Classifier: Programming Language :: Python :: 3.11
Requires-Python: >=3.10
License-File: LICENSE
Requires-Dist: astropy <8,>=6.1
Requires-Dist: lstchain >=0.11.0
Requires-Dist: matplotlib
Requires-Dist: numpy
Requires-Dist: pandas
Requires-Dist: pyyaml
Requires-Dist: prov
Requires-Dist: pydot
Requires-Dist: pydotplus
Requires-Dist: psutil
Requires-Dist: click
Requires-Dist: toml
Requires-Dist: pymongo
Requires-Dist: gammapy ~=1.3
Requires-Dist: tenacity
Provides-Extra: all
Requires-Dist: lstosa[dev,doc,test] ; extra == 'all'
Provides-Extra: dev
Requires-Dist: setuptools-scm ; extra == 'dev'
Provides-Extra: doc
Requires-Dist: sphinx ; extra == 'doc'
Requires-Dist: numpydoc ; extra == 'doc'
Requires-Dist: pydata-sphinx-theme ; extra == 'doc'
Requires-Dist: sphinx-automodapi ; extra == 'doc'
Requires-Dist: sphinx-argparse ; extra == 'doc'
Provides-Extra: test
Requires-Dist: pytest ; extra == 'test'
Requires-Dist: pytest-cov ; extra == 'test'
Requires-Dist: freezegun ; extra == 'test'
